byte_gg_wrapper/__init__.py
byte_gg_wrapper-1.0.3.dist-info/METADATA
byte_gg_wrapper-1.0.3.dist-info/WHEEL
byte_gg_wrapper-1.0.3.dist-info/top_level.txt
byte_gg_wrapper-1.0.3.dist-info/RECORD
